CHANGES.rst
CONTRIBUTORS.rst
DEVELOP.rst
LICENSE.GPL
LICENSE.rst
MANIFEST.in
README.rst
TODO.rst
appveyor.yml
constraints.txt
jsconfig.json
pip-selfcheck.json
requirements.txt
setup.cfg
setup.py
tox.ini
bobtemplates/.DS_Store
bobtemplates/__init__.py
bobtemplates.migration.egg-info/PKG-INFO
bobtemplates.migration.egg-info/SOURCES.txt
bobtemplates.migration.egg-info/dependency_links.txt
bobtemplates.migration.egg-info/entry_points.txt
bobtemplates.migration.egg-info/namespace_packages.txt
bobtemplates.migration.egg-info/not-zip-safe
bobtemplates.migration.egg-info/requires.txt
bobtemplates.migration.egg-info/top_level.txt
bobtemplates/migration/.DS_Store
bobtemplates/migration/__init__.py
bobtemplates/migration/bobregistry.py
bobtemplates/migration/jsonify.py
bobtemplates/migration/jsonify/.mrbob.ini
bobtemplates/migration/jsonify/CHANGES.rst.bob
bobtemplates/migration/jsonify/CONTRIBUTORS.rst.bob
bobtemplates/migration/jsonify/DEVELOP.rst
bobtemplates/migration/jsonify/LICENSE.GPL.bob
bobtemplates/migration/jsonify/LICENSE.rst.bob
bobtemplates/migration/jsonify/MANIFEST.in.bob
bobtemplates/migration/jsonify/README.rst.bob
bobtemplates/migration/jsonify/bobtemplate.cfg.bob
bobtemplates/migration/jsonify/buildout.cfg.bob
bobtemplates/migration/jsonify/plone51.cfg.bob
bobtemplates/migration/jsonify/plone52.cfg.bob
bobtemplates/migration/jsonify/requirements.txt
bobtemplates/migration/jsonify/setup.cfg.bob
bobtemplates/migration/jsonify/setup.py.bob
bobtemplates/migration/jsonify/docs/index.rst.bob
bobtemplates/migration/jsonify/src/+package.namespace+/__init__.py
bobtemplates/migration/jsonify/src/+package.namespace+/+package.name+/.DS_Store
bobtemplates/migration/jsonify/src/+package.namespace+/+package.name+/__init__.py
bobtemplates/migration/jsonify/src/+package.namespace+/+package.name+/configure.zcml.bob
bobtemplates/migration/jsonify/src/+package.namespace+/+package.name+/upgrades.py.bob
bobtemplates/migration/jsonify/src/+package.namespace+/+package.name+/import/__init__.py
bobtemplates/migration/jsonify/src/+package.namespace+/+package.name+/import/blueprints.py
bobtemplates/migration/jsonify/src/+package.namespace+/+package.name+/import/configure.zcml.bob
bobtemplates/migration/jsonify/src/+package.namespace+/+package.name+/import/import_content.cfg.bob
